{
    "course":[
        {
            "courseID": 1,
            "courseName": "Course1",
            "department": "Cisc"
        }
    ],
    "teacher":[
        {
            "teacherID": 1,
            "teacherName": "tName",
            "department": "Cisc"
        }
    ],
    "class":[
        {
            "courseID": 1,
            "teacherID": 1,
            "classID": 1,
            "meanGrade": 100,
            "medianGrade": 100
        }
    ],
    "student":[
        {
            "studentIDNumber": 702000000,
            "name": "Student Name",
            "email": "pname@udel.edu",
            "majorDep": "Cisc"
        }
    ],
    "studentInClass":[
        {
            "studentID": "pname@udel.edu",
            "courseID": 1,
            "studentInClassID": 1,
            "meanGrade": 100,
            "medianGrade": 100
        }
    ],
    "test":[
        {
            "classID": 1,
            "testID": 1,
            "meanScore": 100,
            "medianScore": 100,
            "std": 1
        }
    ],
    "questionsMC":[
        {
            "testID": 1,
            "questionID": 1,
            "optional": 0,
            "question": "What is the answer",
            "answer": "b",
            "aCount": "0",
            "bCount": "1",
            "cCount": "0",
            "dCount": "0",
            "eCount": "0"
        }
    ],
    "questionsP":[
        {
            "testID": 2,
            "questionID": 1,
            "optional": 0,
            "question": "What is the answer",
            "correct": 1,
            "incorrect": 0
        }
    ],
    "questionResponse":[
        {
            "questionID": 1,
            "studentID":"pname@udel.edu",
            "response": "b",
            "biserialCorrelation": 0
        },
        {
            "questionID": 2,
            "studentID":"pname@udel.edu",
            "response": "NA",
            "biserialCorrelation": 0
        }
    ]
}